examples/__init__.py
examples/example_native_query_executor.py
examples/example_simple_query_executor.py
psycopg2_wrapper/DatabaseConnector.py
psycopg2_wrapper/NativeQueryExecutor.py
psycopg2_wrapper/SimpleQueryExecutor.py
psycopg2_wrapper/__init__.py
tests/__init__.py
tests/test_database_connector.py
tests/test_native_query_executor.py
tests/test_simple_query_executor.py
psycopg2_wrappers-1.0.2.dist-info/LICENCE
psycopg2_wrappers-1.0.2.dist-info/METADATA
psycopg2_wrappers-1.0.2.dist-info/WHEEL
psycopg2_wrappers-1.0.2.dist-info/top_level.txt
psycopg2_wrappers-1.0.2.dist-info/RECORD
