Metadata-Version: 2.2
Name: psycopg2-wrappers
Version: 1.0.2
Summary: psycopg2-wrapper is a wrapper for psycopg2 that makes it easier to use.
Author: zestones
Author-email: idrissbenguezzou@gmail.com
Classifier: Programming Language :: Python :: 3
Classifier: License :: OSI Approved :: MIT License
Classifier: Operating System :: OS Independent
License-File: LICENCE
Requires-Dist: psycopg2-binary
Dynamic: author
Dynamic: author-email
Dynamic: classifier
Dynamic: description
Dynamic: description-content-type
Dynamic: requires-dist
Dynamic: summary
